tasksqwerty/__init__.py
tasksqwerty-0.1.dist-info/METADATA
tasksqwerty-0.1.dist-info/WHEEL
tasksqwerty-0.1.dist-info/top_level.txt
tasksqwerty-0.1.dist-info/RECORD
