Metadata-Version: 2.1
Name: tasksqwerty
Version: 0.1
Summary: test todo list
Home-page: http://github.com/perfectsmile/tasks
Author: jzeedyt
Author-email: jzeedyt@gmail.com
Keywords: pip,todolist,example
